{
    "version": 2,
    "cmakeMinimumRequired": {
        "major": 3,
        "minor": 20,
        "patch": 0
    },
    "configurePresets": [
        {
            "name": "default",
            "displayName": "Default Config (Win)",
            "description": "Default build using Visual Stuido and vcpkg",
            "generator": "Visual Studio 17 2022",
            "binaryDir": "${sourceDir}/build",
            "cacheVariables": {
                "CMAKE_TOOLCHAIN_FILE": "${sourceDir}/vcpkg/scripts/buildsystems/vcpkg.cmake"
            }
        }
    ]
}